rapids_dependency_file_generator/__init__.py
rapids_dependency_file_generator/_cli.py
rapids_dependency_file_generator/_config.py
rapids_dependency_file_generator/_constants.py
rapids_dependency_file_generator/_rapids_dependency_file_generator.py
rapids_dependency_file_generator/_rapids_dependency_file_validator.py
rapids_dependency_file_generator/_version.py
rapids_dependency_file_generator/_warnings.py
rapids_dependency_file_generator/py.typed
rapids_dependency_file_generator/schema.json
rapids_dependency_file_generator-1.20.2.dist-info/licenses/LICENSE
rapids_dependency_file_generator-1.20.2.dist-info/METADATA
rapids_dependency_file_generator-1.20.2.dist-info/WHEEL
rapids_dependency_file_generator-1.20.2.dist-info/entry_points.txt
rapids_dependency_file_generator-1.20.2.dist-info/top_level.txt
rapids_dependency_file_generator-1.20.2.dist-info/RECORD
