Metadata-Version: 2.4
Name: rapids-dependency-file-generator
Version: 1.20.2
Summary: Tool for generating RAPIDS environment files
Author-email: RAPIDS Development Team <pypi@rapids.ai>
License-Expression: Apache-2.0
Project-URL: homepage, https://github.com/rapidsai/dependency-file-generator
Classifier: Programming Language :: Python :: 3
Requires-Python: >=3.9
License-File: LICENSE
Requires-Dist: PyYAML
Requires-Dist: jsonschema
Requires-Dist: tomlkit
Dynamic: license-file
